{"code":"14035","nom":"Balleroy-sur-Drôme","tour1":[{"bureau":"0001","inscrits":627,"votants":429,"abstentions":198,"exprimes":419,"blancs":9,"nuls":1,"results":[{"nuance":"RN","nom":"CHAPRON","prenom":"Philippe","voix":175,"elu":false,"pct":41.77},{"nuance":"UG","nom":"DUPONT-FEDERICI","prenom":"Thomas","voix":99,"elu":false,"pct":23.63},{"nuance":"ENS","nom":"BOUYX","prenom":"Bertrand","voix":89,"elu":false,"pct":21.24},{"nuance":"DVD","nom":"NOUVELOT","prenom":"Cédric","voix":44,"elu":false,"pct":10.5},{"nuance":"DSV","nom":"GÉREUX","prenom":"Jean-Alexis","voix":5,"elu":false,"pct":1.19},{"nuance":"EXG","nom":"PELTRE","prenom":"Isabelle","voix":4,"elu":false,"pct":0.95},{"nuance":"REC","nom":"DESCLOS","prenom":"Tony","voix":3,"elu":false,"pct":0.72}],"participation":68.42,"libelle":"Balleroy Sur Drome","adresse":"Mairie Place Du Marché, 14490 Balleroy Sur Drome","lat":49.180963,"lon":-0.83797},{"bureau":"0002","inscrits":347,"votants":249,"abstentions":98,"exprimes":242,"blancs":5,"nuls":2,"results":[{"nuance":"RN","nom":"CHAPRON","prenom":"Philippe","voix":126,"elu":false,"pct":52.07},{"nuance":"DVD","nom":"NOUVELOT","prenom":"Cédric","voix":37,"elu":false,"pct":15.29},{"nuance":"UG","nom":"DUPONT-FEDERICI","prenom":"Thomas","voix":37,"elu":false,"pct":15.29},{"nuance":"ENS","nom":"BOUYX","prenom":"Bertrand","voix":33,"elu":false,"pct":13.64},{"nuance":"DSV","nom":"GÉREUX","prenom":"Jean-Alexis","voix":3,"elu":false,"pct":1.24},{"nuance":"EXG","nom":"PELTRE","prenom":"Isabelle","voix":3,"elu":false,"pct":1.24},{"nuance":"REC","nom":"DESCLOS","prenom":"Tony","voix":3,"elu":false,"pct":1.24}],"participation":71.76,"libelle":"Balleroy Sur Drome","adresse":"Mairie Route De Bayeux, 14490 Balleroy Sur Drome","lat":49.208706,"lon":-0.828766}],"tour2":[{"bureau":"0001","inscrits":627,"votants":427,"abstentions":200,"exprimes":398,"blancs":4,"nuls":25,"results":[{"nuance":"RN","nom":"CHAPRON","prenom":"Philippe","voix":201,"elu":false,"pct":50.5},{"nuance":"ENS","nom":"BOUYX","prenom":"Bertrand","voix":197,"elu":true,"pct":49.5}],"participation":68.1,"libelle":"Balleroy Sur Drome","adresse":"Mairie Place Du Marché, 14490 Balleroy Sur Drome","lat":49.180963,"lon":-0.83797},{"bureau":"0002","inscrits":347,"votants":241,"abstentions":106,"exprimes":238,"blancs":3,"nuls":0,"results":[{"nuance":"RN","nom":"CHAPRON","prenom":"Philippe","voix":137,"elu":false,"pct":57.56},{"nuance":"ENS","nom":"BOUYX","prenom":"Bertrand","voix":101,"elu":true,"pct":42.44}],"participation":69.45,"libelle":"Balleroy Sur Drome","adresse":"Mairie Route De Bayeux, 14490 Balleroy Sur Drome","lat":49.208706,"lon":-0.828766}]}