{"code":"14322","nom":"Guéron","tour1":[{"bureau":"1","inscrits":191,"votants":130,"abstentions":61,"exprimes":128,"blancs":2,"nuls":0,"results":[{"nuance":"ENS","nom":"BOUYX","prenom":"Bertrand","voix":49,"elu":false,"pct":38.28},{"nuance":"RN","nom":"CHAPRON","prenom":"Philippe","voix":33,"elu":false,"pct":25.78},{"nuance":"UG","nom":"DUPONT-FEDERICI","prenom":"Thomas","voix":21,"elu":false,"pct":16.41},{"nuance":"DVD","nom":"NOUVELOT","prenom":"Cédric","voix":18,"elu":false,"pct":14.06},{"nuance":"DSV","nom":"GÉREUX","prenom":"Jean-Alexis","voix":4,"elu":false,"pct":3.13},{"nuance":"REC","nom":"DESCLOS","prenom":"Tony","voix":2,"elu":false,"pct":1.56},{"nuance":"EXG","nom":"PELTRE","prenom":"Isabelle","voix":1,"elu":false,"pct":0.78}],"participation":68.06,"libelle":null,"adresse":null,"lat":null,"lon":null}],"tour2":[{"bureau":"0001","inscrits":191,"votants":130,"abstentions":61,"exprimes":118,"blancs":10,"nuls":2,"results":[{"nuance":"ENS","nom":"BOUYX","prenom":"Bertrand","voix":76,"elu":true,"pct":64.41},{"nuance":"RN","nom":"CHAPRON","prenom":"Philippe","voix":42,"elu":false,"pct":35.59}],"participation":68.06,"libelle":"Mairie","adresse":"Guéron","lat":null,"lon":null}]}