{"code":"27133","nom":"Caumont","legislatives":{"tour1":[{"bureau":"0001","inscrits":929,"votants":696,"abstentions":233,"exprimes":682,"blancs":8,"nuls":6,"results":[{"nuance":"RN","nom":"MAUVIEUX","prenom":"Kévin","voix":270,"elu":false,"pct":39.59},{"nuance":"ENS","nom":"TAMARELLE VERHAEGHE","prenom":"Marie","voix":164,"elu":false,"pct":24.05},{"nuance":"UG","nom":"TURPIN","prenom":"Jean-Christophe","voix":144,"elu":false,"pct":21.11},{"nuance":"DVC","nom":"ELEXHAUSER","prenom":"Thomas","voix":81,"elu":false,"pct":11.88},{"nuance":"EXG","nom":"HUARD","prenom":"Marie-Noëlle","voix":14,"elu":false,"pct":2.05},{"nuance":"REC","nom":"DARIC","prenom":"Didier","voix":9,"elu":false,"pct":1.32}],"participation":74.92,"libelle":"Foyer Communal","adresse":"2 Rue Des Trois Epines, 27310 Caumont","lat":49.368789,"lon":0.894947}],"tour2":[{"bureau":"0001","inscrits":929,"votants":688,"abstentions":241,"exprimes":645,"blancs":35,"nuls":8,"results":[{"nuance":"ENS","nom":"TAMARELLE VERHAEGHE","prenom":"Marie","voix":324,"elu":false,"pct":50.23},{"nuance":"RN","nom":"MAUVIEUX","prenom":"Kévin","voix":321,"elu":true,"pct":49.77}],"participation":74.06,"libelle":"Foyer Communal","adresse":"2 Rue Des Trois Epines, 27310 Caumont","lat":49.368789,"lon":0.894947}]},"presidentielle":{"tour1":[{"bureau":"0001","inscrits":917,"votants":728,"abstentions":189,"exprimes":717,"blancs":9,"nuls":2,"results":[{"nuance":"ENS","nom":"MACRON","prenom":"Emmanuel","voix":231,"elu":false,"pct":32.22},{"nuance":"RN","nom":"LE PEN","prenom":"Marine","voix":184,"elu":false,"pct":25.66},{"nuance":"FI","nom":"MÉLENCHON","prenom":"Jean-Luc","voix":102,"elu":false,"pct":14.23},{"nuance":"LR","nom":"PÉCRESSE","prenom":"Valérie","voix":56,"elu":false,"pct":7.81},{"nuance":"REC","nom":"ZEMMOUR","prenom":"Éric","voix":41,"elu":false,"pct":5.72},{"nuance":"VEC","nom":"JADOT","prenom":"Yannick","voix":32,"elu":false,"pct":4.46},{"nuance":"COM","nom":"ROUSSEL","prenom":"Fabien","voix":19,"elu":false,"pct":2.65},{"nuance":"DIV","nom":"LASSALLE","prenom":"Jean","voix":19,"elu":false,"pct":2.65},{"nuance":"DVD","nom":"DUPONT-AIGNAN","prenom":"Nicolas","voix":13,"elu":false,"pct":1.81},{"nuance":"EXG","nom":"POUTOU","prenom":"Philippe","voix":9,"elu":false,"pct":1.26},{"nuance":"SOC","nom":"HIDALGO","prenom":"Anne","voix":7,"elu":false,"pct":0.98},{"nuance":"EXG","nom":"ARTHAUD","prenom":"Nathalie","voix":4,"elu":false,"pct":0.56}],"participation":79.39,"libelle":"Foyer Communal","adresse":"2 Rue Des Trois Epines, 27310 Caumont","lat":49.368789,"lon":0.894947}],"tour2":[{"bureau":"0001","inscrits":916,"votants":739,"abstentions":177,"exprimes":673,"blancs":52,"nuls":14,"results":[{"nuance":"ENS","nom":"MACRON","prenom":"Emmanuel","voix":394,"elu":true,"pct":58.54},{"nuance":"RN","nom":"LE PEN","prenom":"Marine","voix":279,"elu":false,"pct":41.46}],"participation":80.68,"libelle":"Foyer Communal","adresse":"2 Rue Des Trois Epines, 27310 Caumont","lat":49.368789,"lon":0.894947}]}}