{"code":"27512","nom":"Saint-Aubin-de-Scellon","tour1":[{"bureau":"0001","inscrits":255,"votants":192,"abstentions":63,"exprimes":181,"blancs":7,"nuls":4,"results":[{"nuance":"RN","nom":"MAUVIEUX","prenom":"Kévin","voix":86,"elu":false,"pct":47.51},{"nuance":"DVC","nom":"ELEXHAUSER","prenom":"Thomas","voix":33,"elu":false,"pct":18.23},{"nuance":"ENS","nom":"TAMARELLE VERHAEGHE","prenom":"Marie","voix":33,"elu":false,"pct":18.23},{"nuance":"UG","nom":"TURPIN","prenom":"Jean-Christophe","voix":18,"elu":false,"pct":9.94},{"nuance":"REC","nom":"DARIC","prenom":"Didier","voix":8,"elu":false,"pct":4.42},{"nuance":"EXG","nom":"HUARD","prenom":"Marie-Noëlle","voix":3,"elu":false,"pct":1.66}],"participation":75.29,"libelle":"Mairie","adresse":"2 Rue De La Mairie, 27230 Saint Aubin De Scellon","lat":49.171647,"lon":0.475182}],"tour2":[{"bureau":"0001","inscrits":255,"votants":197,"abstentions":58,"exprimes":179,"blancs":12,"nuls":6,"results":[{"nuance":"RN","nom":"MAUVIEUX","prenom":"Kévin","voix":111,"elu":true,"pct":62.01},{"nuance":"ENS","nom":"TAMARELLE VERHAEGHE","prenom":"Marie","voix":68,"elu":false,"pct":37.99}],"participation":77.25,"libelle":"Mairie","adresse":"2 Rue De La Mairie, 27230 Saint Aubin De Scellon","lat":49.171647,"lon":0.475182}]}