{"code":"28016","nom":"Les Autels-Villevillon","legislatives":{"tour1":[{"bureau":"0001","inscrits":129,"votants":100,"abstentions":29,"exprimes":97,"blancs":2,"nuls":1,"results":[{"nuance":"RN","nom":"BAY","prenom":"Christophe","voix":54,"elu":false,"pct":55.67},{"nuance":"DVC","nom":"HUWART","prenom":"Harold","voix":23,"elu":false,"pct":23.71},{"nuance":"LR","nom":"MARTIAL","prenom":"Rémi","voix":16,"elu":false,"pct":16.49},{"nuance":"EXG","nom":"CHEVROLLIER","prenom":"Vincent","voix":4,"elu":false,"pct":4.12},{"nuance":"REC","nom":"LAQUA","prenom":"Eric","voix":0,"elu":false,"pct":0}],"participation":77.52,"libelle":"Mairie","adresse":"28330 Les Autels Villevillon","lat":48.176043,"lon":1.003302}],"tour2":[{"bureau":"0001","inscrits":129,"votants":99,"abstentions":30,"exprimes":93,"blancs":3,"nuls":3,"results":[{"nuance":"RN","nom":"BAY","prenom":"Christophe","voix":52,"elu":false,"pct":55.91},{"nuance":"DVC","nom":"HUWART","prenom":"Harold","voix":41,"elu":true,"pct":44.09}],"participation":76.74,"libelle":"Mairie","adresse":"28330 Les Autels Villevillon","lat":48.176043,"lon":1.003302}]},"presidentielle":{"tour1":[{"bureau":"0001","inscrits":126,"votants":108,"abstentions":18,"exprimes":103,"blancs":2,"nuls":3,"results":[{"nuance":"RN","nom":"LE PEN","prenom":"Marine","voix":32,"elu":false,"pct":31.07},{"nuance":"ENS","nom":"MACRON","prenom":"Emmanuel","voix":25,"elu":false,"pct":24.27},{"nuance":"LR","nom":"PÉCRESSE","prenom":"Valérie","voix":13,"elu":false,"pct":12.62},{"nuance":"REC","nom":"ZEMMOUR","prenom":"Éric","voix":12,"elu":false,"pct":11.65},{"nuance":"FI","nom":"MÉLENCHON","prenom":"Jean-Luc","voix":11,"elu":false,"pct":10.68},{"nuance":"DIV","nom":"LASSALLE","prenom":"Jean","voix":5,"elu":false,"pct":4.85},{"nuance":"VEC","nom":"JADOT","prenom":"Yannick","voix":2,"elu":false,"pct":1.94},{"nuance":"COM","nom":"ROUSSEL","prenom":"Fabien","voix":1,"elu":false,"pct":0.97},{"nuance":"EXG","nom":"POUTOU","prenom":"Philippe","voix":1,"elu":false,"pct":0.97},{"nuance":"DVD","nom":"DUPONT-AIGNAN","prenom":"Nicolas","voix":1,"elu":false,"pct":0.97},{"nuance":"EXG","nom":"ARTHAUD","prenom":"Nathalie","voix":0,"elu":false,"pct":0},{"nuance":"SOC","nom":"HIDALGO","prenom":"Anne","voix":0,"elu":false,"pct":0}],"participation":85.71,"libelle":"Mairie","adresse":"28330 Les Autels Villevillon","lat":48.176043,"lon":1.003302}],"tour2":[{"bureau":"0001","inscrits":126,"votants":105,"abstentions":21,"exprimes":96,"blancs":7,"nuls":2,"results":[{"nuance":"RN","nom":"LE PEN","prenom":"Marine","voix":53,"elu":false,"pct":55.21},{"nuance":"ENS","nom":"MACRON","prenom":"Emmanuel","voix":43,"elu":true,"pct":44.79}],"participation":83.33,"libelle":"Mairie","adresse":"28330 Les Autels Villevillon","lat":48.176043,"lon":1.003302}]}}