{"code":"30042","nom":"Boisset-et-Gaujac","tour1":[{"bureau":"0001","inscrits":1046,"votants":729,"abstentions":317,"exprimes":720,"blancs":3,"nuls":6,"results":[{"nuance":"UXD","nom":"ALLEGRET-PILOT","prenom":"Alexandre","voix":323,"elu":false,"pct":44.86},{"nuance":"UG","nom":"SALA","prenom":"Michel","voix":194,"elu":false,"pct":26.94},{"nuance":"ENS","nom":"DAUFÈS-ROUX","prenom":"Catherine","voix":110,"elu":false,"pct":15.28},{"nuance":"LR","nom":"BOYER","prenom":"Léa","voix":73,"elu":false,"pct":10.14},{"nuance":"DIV","nom":"TRIA","prenom":"Nordine","voix":12,"elu":false,"pct":1.67},{"nuance":"EXG","nom":"OLINET","prenom":"Agnès","voix":8,"elu":false,"pct":1.11},{"nuance":"EXD","nom":"ESPANOL","prenom":"Emmanuel","voix":0,"elu":false,"pct":0}],"participation":69.69,"libelle":"Salle Des Fetes","adresse":"Route D'Anduze, 30140 Boisset Et Gaujac","lat":44.050981,"lon":4.013155},{"bureau":"0002","inscrits":1107,"votants":762,"abstentions":345,"exprimes":741,"blancs":15,"nuls":6,"results":[{"nuance":"UXD","nom":"ALLEGRET-PILOT","prenom":"Alexandre","voix":386,"elu":false,"pct":52.09},{"nuance":"UG","nom":"SALA","prenom":"Michel","voix":177,"elu":false,"pct":23.89},{"nuance":"ENS","nom":"DAUFÈS-ROUX","prenom":"Catherine","voix":94,"elu":false,"pct":12.69},{"nuance":"LR","nom":"BOYER","prenom":"Léa","voix":56,"elu":false,"pct":7.56},{"nuance":"DIV","nom":"TRIA","prenom":"Nordine","voix":16,"elu":false,"pct":2.16},{"nuance":"EXG","nom":"OLINET","prenom":"Agnès","voix":12,"elu":false,"pct":1.62},{"nuance":"EXD","nom":"ESPANOL","prenom":"Emmanuel","voix":0,"elu":false,"pct":0}],"participation":68.83,"libelle":"Halle Des Sports","adresse":"Route De Ribaute, 30140 Boisset Et Gaujac","lat":44.049004,"lon":4.028873}],"tour2":[{"bureau":"0001","inscrits":1046,"votants":738,"abstentions":308,"exprimes":670,"blancs":53,"nuls":15,"results":[{"nuance":"UXD","nom":"ALLEGRET-PILOT","prenom":"Alexandre","voix":407,"elu":true,"pct":60.75},{"nuance":"UG","nom":"SALA","prenom":"Michel","voix":263,"elu":false,"pct":39.25}],"participation":70.55,"libelle":"Salle Des Fetes","adresse":"Route D'Anduze, 30140 Boisset Et Gaujac","lat":44.050981,"lon":4.013155},{"bureau":"0002","inscrits":1107,"votants":779,"abstentions":328,"exprimes":725,"blancs":44,"nuls":10,"results":[{"nuance":"UXD","nom":"ALLEGRET-PILOT","prenom":"Alexandre","voix":451,"elu":true,"pct":62.21},{"nuance":"UG","nom":"SALA","prenom":"Michel","voix":274,"elu":false,"pct":37.79}],"participation":70.37,"libelle":"Halle Des Sports","adresse":"Route De Ribaute, 30140 Boisset Et Gaujac","lat":44.049004,"lon":4.028873}]}