{"code":"33260","nom":"Lugos","tour1":[{"bureau":"1","inscrits":879,"votants":636,"abstentions":243,"exprimes":617,"blancs":16,"nuls":3,"results":[{"nuance":"RN","nom":"MARQUES","prenom":"François-Xavier","voix":287,"elu":false,"pct":46.52},{"nuance":"ENS","nom":"METTE","prenom":"Sophie","voix":159,"elu":false,"pct":25.77},{"nuance":"UG","nom":"MARTINEZ","prenom":"Corinne","voix":151,"elu":false,"pct":24.47},{"nuance":"EXG","nom":"DELCAMP","prenom":"Jean-Philippe","voix":10,"elu":false,"pct":1.62},{"nuance":"REC","nom":"MANTEL","prenom":"Sylvie","voix":10,"elu":false,"pct":1.62}],"participation":72.35,"libelle":null,"adresse":null,"lat":null,"lon":null}],"tour2":[{"bureau":"0001","inscrits":878,"votants":647,"abstentions":231,"exprimes":604,"blancs":36,"nuls":7,"results":[{"nuance":"RN","nom":"MARQUES","prenom":"François-Xavier","voix":321,"elu":false,"pct":53.15},{"nuance":"ENS","nom":"METTE","prenom":"Sophie","voix":283,"elu":true,"pct":46.85}],"participation":73.69,"libelle":"Ecole Primaire","adresse":"20 Rue Des Ecoles, 33830 Lugos","lat":44.484565,"lon":-0.883152}]}