{"code":"53169","nom":"Olivet","tour1":[{"bureau":"1","inscrits":298,"votants":240,"abstentions":58,"exprimes":234,"blancs":3,"nuls":3,"results":[{"nuance":"HOR","nom":"FAVENNEC","prenom":"Yannick","voix":89,"elu":false,"pct":38.03},{"nuance":"RN","nom":"BELL","prenom":"Annie","voix":71,"elu":false,"pct":30.34},{"nuance":"UG","nom":"LEFOULON","prenom":"Stéphanie","voix":70,"elu":false,"pct":29.91},{"nuance":"EXG","nom":"AMELIN","prenom":"Martine","voix":4,"elu":false,"pct":1.71}],"participation":80.54,"libelle":null,"adresse":null,"lat":null,"lon":null}],"tour2":[{"bureau":"0001","inscrits":298,"votants":237,"abstentions":61,"exprimes":229,"blancs":6,"nuls":2,"results":[{"nuance":"HOR","nom":"FAVENNEC","prenom":"Yannick","voix":154,"elu":true,"pct":67.25},{"nuance":"RN","nom":"BELL","prenom":"Annie","voix":75,"elu":false,"pct":32.75}],"participation":79.53,"libelle":"Salle Saint Laurent","adresse":"4 Rue Du Prieuré, 53410 Olivet","lat":48.121455,"lon":-0.919001}]}