{"code":"54513","nom":"Tantonville","legislatives":{"tour1":[{"bureau":"0001","inscrits":436,"votants":305,"abstentions":131,"exprimes":296,"blancs":5,"nuls":4,"results":[{"nuance":"UG","nom":"POTIER","prenom":"Dominique","voix":114,"elu":false,"pct":38.51},{"nuance":"EXD","nom":"PECHER","prenom":"Louis-Joseph","voix":103,"elu":false,"pct":34.8},{"nuance":"LR","nom":"VINOT","prenom":"Quentin","voix":42,"elu":false,"pct":14.19},{"nuance":"EXD","nom":"NUPS","prenom":"Pierre-Nicolas","voix":29,"elu":false,"pct":9.8},{"nuance":"EXG","nom":"AUBERT","prenom":"Miriam","voix":7,"elu":false,"pct":2.36},{"nuance":"DIV","nom":"MATHIEU","prenom":"Edouard","voix":1,"elu":false,"pct":0.34}],"participation":69.95,"libelle":"Mairie","adresse":"54116 Tantonville","lat":48.473082,"lon":6.137731}],"tour2":[{"bureau":"0001","inscrits":436,"votants":283,"abstentions":153,"exprimes":271,"blancs":8,"nuls":4,"results":[{"nuance":"EXD","nom":"PECHER","prenom":"Louis-Joseph","voix":136,"elu":false,"pct":50.18},{"nuance":"UG","nom":"POTIER","prenom":"Dominique","voix":135,"elu":true,"pct":49.82}],"participation":64.91,"libelle":"Mairie","adresse":"54116 Tantonville","lat":48.473082,"lon":6.137731}]},"presidentielle":{"tour1":[{"bureau":"0001","inscrits":418,"votants":311,"abstentions":107,"exprimes":306,"blancs":5,"nuls":0,"results":[{"nuance":"RN","nom":"LE PEN","prenom":"Marine","voix":115,"elu":false,"pct":37.58},{"nuance":"ENS","nom":"MACRON","prenom":"Emmanuel","voix":88,"elu":false,"pct":28.76},{"nuance":"FI","nom":"MÉLENCHON","prenom":"Jean-Luc","voix":36,"elu":false,"pct":11.76},{"nuance":"REC","nom":"ZEMMOUR","prenom":"Éric","voix":14,"elu":false,"pct":4.58},{"nuance":"LR","nom":"PÉCRESSE","prenom":"Valérie","voix":13,"elu":false,"pct":4.25},{"nuance":"VEC","nom":"JADOT","prenom":"Yannick","voix":12,"elu":false,"pct":3.92},{"nuance":"COM","nom":"ROUSSEL","prenom":"Fabien","voix":8,"elu":false,"pct":2.61},{"nuance":"DVD","nom":"DUPONT-AIGNAN","prenom":"Nicolas","voix":8,"elu":false,"pct":2.61},{"nuance":"DIV","nom":"LASSALLE","prenom":"Jean","voix":5,"elu":false,"pct":1.63},{"nuance":"SOC","nom":"HIDALGO","prenom":"Anne","voix":4,"elu":false,"pct":1.31},{"nuance":"EXG","nom":"ARTHAUD","prenom":"Nathalie","voix":2,"elu":false,"pct":0.65},{"nuance":"EXG","nom":"POUTOU","prenom":"Philippe","voix":1,"elu":false,"pct":0.33}],"participation":74.4,"libelle":"Mairie","adresse":"54116 Tantonville","lat":48.473082,"lon":6.137731}],"tour2":[{"bureau":"0001","inscrits":416,"votants":340,"abstentions":76,"exprimes":316,"blancs":20,"nuls":4,"results":[{"nuance":"RN","nom":"LE PEN","prenom":"Marine","voix":168,"elu":false,"pct":53.16},{"nuance":"ENS","nom":"MACRON","prenom":"Emmanuel","voix":148,"elu":true,"pct":46.84}],"participation":81.73,"libelle":"Mairie","adresse":"54116 Tantonville","lat":48.473082,"lon":6.137731}]}}