{"code":"56101","nom":"Languidic","tour1":[{"bureau":"0001","inscrits":989,"votants":705,"abstentions":284,"exprimes":684,"blancs":19,"nuls":2,"results":[{"nuance":"ENS","nom":"JACQUES","prenom":"Jean-Michel","voix":256,"elu":false,"pct":37.43},{"nuance":"RN","nom":"GUIHOT-VIEIRA","prenom":"Nathalie","voix":235,"elu":false,"pct":34.36},{"nuance":"UG","nom":"BAUDRY","prenom":"Jean-Michel","voix":141,"elu":false,"pct":20.61},{"nuance":"DVD","nom":"BARACH","prenom":"Daniel","voix":32,"elu":false,"pct":4.68},{"nuance":"EXG","nom":"LAGREE","prenom":"Kelig","voix":17,"elu":false,"pct":2.49},{"nuance":"DSV","nom":"CHARLERY","prenom":"Valère","voix":3,"elu":false,"pct":0.44}],"participation":71.28,"libelle":"Bureau De Vote 1","adresse":"Salle Jo Huitel, 56440 Languidic","lat":47.865665,"lon":-3.177989},{"bureau":"0002","inscrits":934,"votants":651,"abstentions":283,"exprimes":636,"blancs":10,"nuls":5,"results":[{"nuance":"RN","nom":"GUIHOT-VIEIRA","prenom":"Nathalie","voix":242,"elu":false,"pct":38.05},{"nuance":"ENS","nom":"JACQUES","prenom":"Jean-Michel","voix":211,"elu":false,"pct":33.18},{"nuance":"UG","nom":"BAUDRY","prenom":"Jean-Michel","voix":121,"elu":false,"pct":19.03},{"nuance":"DVD","nom":"BARACH","prenom":"Daniel","voix":35,"elu":false,"pct":5.5},{"nuance":"DSV","nom":"CHARLERY","prenom":"Valère","voix":15,"elu":false,"pct":2.36},{"nuance":"EXG","nom":"LAGREE","prenom":"Kelig","voix":12,"elu":false,"pct":1.89}],"participation":69.7,"libelle":"Bureau De Vote 2","adresse":"Salle Jo Huitel, 56440 Languidic","lat":47.865665,"lon":-3.177989},{"bureau":"0003","inscrits":943,"votants":671,"abstentions":272,"exprimes":647,"blancs":15,"nuls":9,"results":[{"nuance":"RN","nom":"GUIHOT-VIEIRA","prenom":"Nathalie","voix":246,"elu":false,"pct":38.02},{"nuance":"ENS","nom":"JACQUES","prenom":"Jean-Michel","voix":209,"elu":false,"pct":32.3},{"nuance":"UG","nom":"BAUDRY","prenom":"Jean-Michel","voix":141,"elu":false,"pct":21.79},{"nuance":"DVD","nom":"BARACH","prenom":"Daniel","voix":27,"elu":false,"pct":4.17},{"nuance":"EXG","nom":"LAGREE","prenom":"Kelig","voix":13,"elu":false,"pct":2.01},{"nuance":"DSV","nom":"CHARLERY","prenom":"Valère","voix":11,"elu":false,"pct":1.7}],"participation":71.16,"libelle":"Bureau De Vote 3","adresse":"Salle Jo Huitel, 56440 Languidic","lat":47.865665,"lon":-3.177989},{"bureau":"0004","inscrits":1140,"votants":751,"abstentions":389,"exprimes":725,"blancs":19,"nuls":7,"results":[{"nuance":"RN","nom":"GUIHOT-VIEIRA","prenom":"Nathalie","voix":308,"elu":false,"pct":42.48},{"nuance":"ENS","nom":"JACQUES","prenom":"Jean-Michel","voix":185,"elu":false,"pct":25.52},{"nuance":"UG","nom":"BAUDRY","prenom":"Jean-Michel","voix":168,"elu":false,"pct":23.17},{"nuance":"DVD","nom":"BARACH","prenom":"Daniel","voix":39,"elu":false,"pct":5.38},{"nuance":"EXG","nom":"LAGREE","prenom":"Kelig","voix":14,"elu":false,"pct":1.93},{"nuance":"DSV","nom":"CHARLERY","prenom":"Valère","voix":11,"elu":false,"pct":1.52}],"participation":65.88,"libelle":"Bureau De Vote 4","adresse":"Salle Jo Huitel, 56440 Languidic","lat":47.865665,"lon":-3.177989},{"bureau":"0005","inscrits":1014,"votants":720,"abstentions":294,"exprimes":698,"blancs":14,"nuls":8,"results":[{"nuance":"RN","nom":"GUIHOT-VIEIRA","prenom":"Nathalie","voix":258,"elu":false,"pct":36.96},{"nuance":"ENS","nom":"JACQUES","prenom":"Jean-Michel","voix":223,"elu":false,"pct":31.95},{"nuance":"UG","nom":"BAUDRY","prenom":"Jean-Michel","voix":143,"elu":false,"pct":20.49},{"nuance":"DVD","nom":"BARACH","prenom":"Daniel","voix":40,"elu":false,"pct":5.73},{"nuance":"EXG","nom":"LAGREE","prenom":"Kelig","voix":21,"elu":false,"pct":3.01},{"nuance":"DSV","nom":"CHARLERY","prenom":"Valère","voix":13,"elu":false,"pct":1.86}],"participation":71.01,"libelle":"Bureau De Vote 5","adresse":"Salle Les Menhirs, 56440 Languidic","lat":47.861403,"lon":-3.090464},{"bureau":"0006","inscrits":903,"votants":631,"abstentions":272,"exprimes":603,"blancs":19,"nuls":9,"results":[{"nuance":"RN","nom":"GUIHOT-VIEIRA","prenom":"Nathalie","voix":213,"elu":false,"pct":35.32},{"nuance":"ENS","nom":"JACQUES","prenom":"Jean-Michel","voix":189,"elu":false,"pct":31.34},{"nuance":"UG","nom":"BAUDRY","prenom":"Jean-Michel","voix":133,"elu":false,"pct":22.06},{"nuance":"DVD","nom":"BARACH","prenom":"Daniel","voix":46,"elu":false,"pct":7.63},{"nuance":"EXG","nom":"LAGREE","prenom":"Kelig","voix":12,"elu":false,"pct":1.99},{"nuance":"DSV","nom":"CHARLERY","prenom":"Valère","voix":10,"elu":false,"pct":1.66}],"participation":69.88,"libelle":"Bureau De Vote 6","adresse":"Salle Jo Huitel, 56440 Languidic","lat":47.865665,"lon":-3.177989},{"bureau":"0007","inscrits":496,"votants":353,"abstentions":143,"exprimes":349,"blancs":2,"nuls":2,"results":[{"nuance":"RN","nom":"GUIHOT-VIEIRA","prenom":"Nathalie","voix":125,"elu":false,"pct":35.82},{"nuance":"ENS","nom":"JACQUES","prenom":"Jean-Michel","voix":102,"elu":false,"pct":29.23},{"nuance":"UG","nom":"BAUDRY","prenom":"Jean-Michel","voix":102,"elu":false,"pct":29.23},{"nuance":"DVD","nom":"BARACH","prenom":"Daniel","voix":12,"elu":false,"pct":3.44},{"nuance":"EXG","nom":"LAGREE","prenom":"Kelig","voix":4,"elu":false,"pct":1.15},{"nuance":"DSV","nom":"CHARLERY","prenom":"Valère","voix":4,"elu":false,"pct":1.15}],"participation":71.17,"libelle":"Bureau De Vote 7","adresse":"Rue De L'Ecole - Tréauray, 56440 Languidic","lat":47.786827,"lon":-3.160929}],"tour2":[{"bureau":"0001","inscrits":991,"votants":714,"abstentions":277,"exprimes":673,"blancs":33,"nuls":8,"results":[{"nuance":"ENS","nom":"JACQUES","prenom":"Jean-Michel","voix":412,"elu":true,"pct":61.22},{"nuance":"RN","nom":"GUIHOT-VIEIRA","prenom":"Nathalie","voix":261,"elu":false,"pct":38.78}],"participation":72.05,"libelle":"Bureau De Vote 1","adresse":"Salle Jo Huitel, 56440 Languidic","lat":47.865665,"lon":-3.177989},{"bureau":"0002","inscrits":933,"votants":662,"abstentions":271,"exprimes":623,"blancs":35,"nuls":4,"results":[{"nuance":"ENS","nom":"JACQUES","prenom":"Jean-Michel","voix":356,"elu":true,"pct":57.14},{"nuance":"RN","nom":"GUIHOT-VIEIRA","prenom":"Nathalie","voix":267,"elu":false,"pct":42.86}],"participation":70.95,"libelle":"Bureau De Vote 2","adresse":"Salle Jo Huitel, 56440 Languidic","lat":47.865665,"lon":-3.177989},{"bureau":"0003","inscrits":943,"votants":671,"abstentions":272,"exprimes":614,"blancs":36,"nuls":21,"results":[{"nuance":"ENS","nom":"JACQUES","prenom":"Jean-Michel","voix":344,"elu":true,"pct":56.03},{"nuance":"RN","nom":"GUIHOT-VIEIRA","prenom":"Nathalie","voix":270,"elu":false,"pct":43.97}],"participation":71.16,"libelle":"Bureau De Vote 3","adresse":"Salle Jo Huitel, 56440 Languidic","lat":47.865665,"lon":-3.177989},{"bureau":"0004","inscrits":1140,"votants":765,"abstentions":375,"exprimes":713,"blancs":42,"nuls":10,"results":[{"nuance":"ENS","nom":"JACQUES","prenom":"Jean-Michel","voix":374,"elu":true,"pct":52.45},{"nuance":"RN","nom":"GUIHOT-VIEIRA","prenom":"Nathalie","voix":339,"elu":false,"pct":47.55}],"participation":67.11,"libelle":"Bureau De Vote 4","adresse":"Salle Jo Huitel, 56440 Languidic","lat":47.865665,"lon":-3.177989},{"bureau":"0005","inscrits":1015,"votants":727,"abstentions":288,"exprimes":690,"blancs":28,"nuls":9,"results":[{"nuance":"ENS","nom":"JACQUES","prenom":"Jean-Michel","voix":399,"elu":true,"pct":57.83},{"nuance":"RN","nom":"GUIHOT-VIEIRA","prenom":"Nathalie","voix":291,"elu":false,"pct":42.17}],"participation":71.63,"libelle":"Bureau De Vote 5","adresse":"Salle Les Menhirs, 56440 Languidic","lat":47.861403,"lon":-3.090464},{"bureau":"0006","inscrits":903,"votants":642,"abstentions":261,"exprimes":598,"blancs":30,"nuls":14,"results":[{"nuance":"ENS","nom":"JACQUES","prenom":"Jean-Michel","voix":340,"elu":true,"pct":56.86},{"nuance":"RN","nom":"GUIHOT-VIEIRA","prenom":"Nathalie","voix":258,"elu":false,"pct":43.14}],"participation":71.1,"libelle":"Bureau De Vote 6","adresse":"Salle Jo Huitel, 56440 Languidic","lat":47.865665,"lon":-3.177989},{"bureau":"0007","inscrits":496,"votants":352,"abstentions":144,"exprimes":338,"blancs":6,"nuls":8,"results":[{"nuance":"ENS","nom":"JACQUES","prenom":"Jean-Michel","voix":201,"elu":true,"pct":59.47},{"nuance":"RN","nom":"GUIHOT-VIEIRA","prenom":"Nathalie","voix":137,"elu":false,"pct":40.53}],"participation":70.97,"libelle":"Bureau De Vote 7","adresse":"Rue De L'Ecole - Tréauray, 56440 Languidic","lat":47.786827,"lon":-3.160929}]}