{"code":"57620","nom":"Sainte-Marie-aux-Chênes","legislatives":{"tour1":[{"bureau":"0001","inscrits":744,"votants":462,"abstentions":282,"exprimes":439,"blancs":16,"nuls":7,"results":[{"nuance":"RN","nom":"LALOUX","prenom":"Grégoire","voix":231,"elu":false,"pct":52.62},{"nuance":"ENS","nom":"BELHADDAD","prenom":"Belkhir","voix":104,"elu":false,"pct":23.69},{"nuance":"UG","nom":"FELIX","prenom":"Vincent","voix":81,"elu":false,"pct":18.45},{"nuance":"EXG","nom":"GEORGET","prenom":"Didier","voix":8,"elu":false,"pct":1.82},{"nuance":"DSV","nom":"JACQUES","prenom":"Jean-François","voix":6,"elu":false,"pct":1.37},{"nuance":"DIV","nom":"COSTA","prenom":"Américo Jonas","voix":3,"elu":false,"pct":0.68},{"nuance":"EXG","nom":"LEJAL","prenom":"Célia","voix":3,"elu":false,"pct":0.68},{"nuance":"DIV","nom":"DUSO-BAUDUIN","prenom":"Stephen","voix":3,"elu":false,"pct":0.68}],"participation":62.1,"libelle":"Complexe Sportif Et Culturel","adresse":"5 bis Rue Arago, 57255 Sainte Marie Aux Chenes","lat":49.190598,"lon":5.998183},{"bureau":"0002","inscrits":838,"votants":533,"abstentions":305,"exprimes":516,"blancs":15,"nuls":2,"results":[{"nuance":"RN","nom":"LALOUX","prenom":"Grégoire","voix":310,"elu":false,"pct":60.08},{"nuance":"ENS","nom":"BELHADDAD","prenom":"Belkhir","voix":102,"elu":false,"pct":19.77},{"nuance":"UG","nom":"FELIX","prenom":"Vincent","voix":69,"elu":false,"pct":13.37},{"nuance":"DSV","nom":"JACQUES","prenom":"Jean-François","voix":14,"elu":false,"pct":2.71},{"nuance":"DIV","nom":"DUSO-BAUDUIN","prenom":"Stephen","voix":9,"elu":false,"pct":1.74},{"nuance":"EXG","nom":"GEORGET","prenom":"Didier","voix":8,"elu":false,"pct":1.55},{"nuance":"DIV","nom":"COSTA","prenom":"Américo Jonas","voix":4,"elu":false,"pct":0.78},{"nuance":"EXG","nom":"LEJAL","prenom":"Célia","voix":0,"elu":false,"pct":0}],"participation":63.6,"libelle":"Complexe Sportif Et Culturel","adresse":"5 bis Rue Arago, 57255 Sainte Marie Aux Chenes","lat":49.190598,"lon":5.998183},{"bureau":"0003","inscrits":862,"votants":556,"abstentions":306,"exprimes":539,"blancs":10,"nuls":7,"results":[{"nuance":"RN","nom":"LALOUX","prenom":"Grégoire","voix":253,"elu":false,"pct":46.94},{"nuance":"ENS","nom":"BELHADDAD","prenom":"Belkhir","voix":139,"elu":false,"pct":25.79},{"nuance":"UG","nom":"FELIX","prenom":"Vincent","voix":109,"elu":false,"pct":20.22},{"nuance":"DIV","nom":"DUSO-BAUDUIN","prenom":"Stephen","voix":12,"elu":false,"pct":2.23},{"nuance":"DSV","nom":"JACQUES","prenom":"Jean-François","voix":10,"elu":false,"pct":1.86},{"nuance":"EXG","nom":"GEORGET","prenom":"Didier","voix":9,"elu":false,"pct":1.67},{"nuance":"DIV","nom":"COSTA","prenom":"Américo Jonas","voix":6,"elu":false,"pct":1.11},{"nuance":"EXG","nom":"LEJAL","prenom":"Célia","voix":1,"elu":false,"pct":0.19}],"participation":64.5,"libelle":"Complexe Sportif Et Culturel","adresse":"5 bis Rue Arago, 57255 Sainte Marie Aux Chenes","lat":49.190598,"lon":5.998183},{"bureau":"0004","inscrits":762,"votants":482,"abstentions":280,"exprimes":466,"blancs":11,"nuls":5,"results":[{"nuance":"RN","nom":"LALOUX","prenom":"Grégoire","voix":222,"elu":false,"pct":47.64},{"nuance":"ENS","nom":"BELHADDAD","prenom":"Belkhir","voix":115,"elu":false,"pct":24.68},{"nuance":"UG","nom":"FELIX","prenom":"Vincent","voix":103,"elu":false,"pct":22.1},{"nuance":"DIV","nom":"DUSO-BAUDUIN","prenom":"Stephen","voix":11,"elu":false,"pct":2.36},{"nuance":"EXG","nom":"GEORGET","prenom":"Didier","voix":6,"elu":false,"pct":1.29},{"nuance":"DSV","nom":"JACQUES","prenom":"Jean-François","voix":6,"elu":false,"pct":1.29},{"nuance":"DIV","nom":"COSTA","prenom":"Américo Jonas","voix":3,"elu":false,"pct":0.64},{"nuance":"EXG","nom":"LEJAL","prenom":"Célia","voix":0,"elu":false,"pct":0}],"participation":63.25,"libelle":"Complexe Sportif Et Culturel","adresse":"5 BIS Rue Arago, 57255 Sainte Marie Aux Chenes","lat":49.190598,"lon":5.998183}],"tour2":[{"bureau":"0001","inscrits":744,"votants":451,"abstentions":293,"exprimes":428,"blancs":18,"nuls":5,"results":[{"nuance":"RN","nom":"LALOUX","prenom":"Grégoire","voix":238,"elu":false,"pct":55.61},{"nuance":"ENS","nom":"BELHADDAD","prenom":"Belkhir","voix":190,"elu":true,"pct":44.39}],"participation":60.62,"libelle":"Complexe Sportif Et Culturel","adresse":"5 bis Rue Arago, 57255 Sainte Marie Aux Chenes","lat":49.190598,"lon":5.998183},{"bureau":"0002","inscrits":838,"votants":562,"abstentions":276,"exprimes":537,"blancs":22,"nuls":3,"results":[{"nuance":"RN","nom":"LALOUX","prenom":"Grégoire","voix":342,"elu":false,"pct":63.69},{"nuance":"ENS","nom":"BELHADDAD","prenom":"Belkhir","voix":195,"elu":true,"pct":36.31}],"participation":67.06,"libelle":"Complexe Sportif Et Culturel","adresse":"5 bis Rue Arago, 57255 Sainte Marie Aux Chenes","lat":49.190598,"lon":5.998183},{"bureau":"0003","inscrits":862,"votants":569,"abstentions":293,"exprimes":535,"blancs":26,"nuls":8,"results":[{"nuance":"RN","nom":"LALOUX","prenom":"Grégoire","voix":273,"elu":false,"pct":51.03},{"nuance":"ENS","nom":"BELHADDAD","prenom":"Belkhir","voix":262,"elu":true,"pct":48.97}],"participation":66.01,"libelle":"Complexe Sportif Et Culturel","adresse":"5 bis Rue Arago, 57255 Sainte Marie Aux Chenes","lat":49.190598,"lon":5.998183},{"bureau":"0004","inscrits":763,"votants":501,"abstentions":262,"exprimes":479,"blancs":20,"nuls":2,"results":[{"nuance":"RN","nom":"LALOUX","prenom":"Grégoire","voix":263,"elu":false,"pct":54.91},{"nuance":"ENS","nom":"BELHADDAD","prenom":"Belkhir","voix":216,"elu":true,"pct":45.09}],"participation":65.66,"libelle":"Complexe Sportif Et Culturel","adresse":"5 BIS Rue Arago, 57255 Sainte Marie Aux Chenes","lat":49.190598,"lon":5.998183}]},"presidentielle":{"tour1":[{"bureau":"0001","inscrits":751,"votants":539,"abstentions":212,"exprimes":528,"blancs":5,"nuls":6,"results":[{"nuance":"RN","nom":"LE PEN","prenom":"Marine","voix":189,"elu":false,"pct":35.8},{"nuance":"ENS","nom":"MACRON","prenom":"Emmanuel","voix":131,"elu":false,"pct":24.81},{"nuance":"FI","nom":"MÉLENCHON","prenom":"Jean-Luc","voix":88,"elu":false,"pct":16.67},{"nuance":"REC","nom":"ZEMMOUR","prenom":"Éric","voix":32,"elu":false,"pct":6.06},{"nuance":"COM","nom":"ROUSSEL","prenom":"Fabien","voix":22,"elu":false,"pct":4.17},{"nuance":"VEC","nom":"JADOT","prenom":"Yannick","voix":17,"elu":false,"pct":3.22},{"nuance":"DIV","nom":"LASSALLE","prenom":"Jean","voix":13,"elu":false,"pct":2.46},{"nuance":"LR","nom":"PÉCRESSE","prenom":"Valérie","voix":13,"elu":false,"pct":2.46},{"nuance":"DVD","nom":"DUPONT-AIGNAN","prenom":"Nicolas","voix":10,"elu":false,"pct":1.89},{"nuance":"EXG","nom":"POUTOU","prenom":"Philippe","voix":8,"elu":false,"pct":1.52},{"nuance":"SOC","nom":"HIDALGO","prenom":"Anne","voix":3,"elu":false,"pct":0.57},{"nuance":"EXG","nom":"ARTHAUD","prenom":"Nathalie","voix":2,"elu":false,"pct":0.38}],"participation":71.77,"libelle":"Complexe Sportif Et Culturel","adresse":"5 bis Rue Arago, 57255 Sainte Marie Aux Chenes","lat":49.190598,"lon":5.998183},{"bureau":"0002","inscrits":765,"votants":575,"abstentions":190,"exprimes":558,"blancs":15,"nuls":2,"results":[{"nuance":"RN","nom":"LE PEN","prenom":"Marine","voix":224,"elu":false,"pct":40.14},{"nuance":"ENS","nom":"MACRON","prenom":"Emmanuel","voix":135,"elu":false,"pct":24.19},{"nuance":"FI","nom":"MÉLENCHON","prenom":"Jean-Luc","voix":85,"elu":false,"pct":15.23},{"nuance":"REC","nom":"ZEMMOUR","prenom":"Éric","voix":51,"elu":false,"pct":9.14},{"nuance":"DVD","nom":"DUPONT-AIGNAN","prenom":"Nicolas","voix":15,"elu":false,"pct":2.69},{"nuance":"DIV","nom":"LASSALLE","prenom":"Jean","voix":10,"elu":false,"pct":1.79},{"nuance":"VEC","nom":"JADOT","prenom":"Yannick","voix":9,"elu":false,"pct":1.61},{"nuance":"LR","nom":"PÉCRESSE","prenom":"Valérie","voix":9,"elu":false,"pct":1.61},{"nuance":"COM","nom":"ROUSSEL","prenom":"Fabien","voix":8,"elu":false,"pct":1.43},{"nuance":"EXG","nom":"ARTHAUD","prenom":"Nathalie","voix":4,"elu":false,"pct":0.72},{"nuance":"SOC","nom":"HIDALGO","prenom":"Anne","voix":4,"elu":false,"pct":0.72},{"nuance":"EXG","nom":"POUTOU","prenom":"Philippe","voix":4,"elu":false,"pct":0.72}],"participation":75.16,"libelle":"Complexe Sportif Et Culturel","adresse":"5 bis Rue Arago, 57255 Sainte Marie Aux Chenes","lat":49.190598,"lon":5.998183},{"bureau":"0003","inscrits":842,"votants":635,"abstentions":207,"exprimes":623,"blancs":8,"nuls":4,"results":[{"nuance":"ENS","nom":"MACRON","prenom":"Emmanuel","voix":185,"elu":false,"pct":29.7},{"nuance":"RN","nom":"LE PEN","prenom":"Marine","voix":184,"elu":false,"pct":29.53},{"nuance":"FI","nom":"MÉLENCHON","prenom":"Jean-Luc","voix":113,"elu":false,"pct":18.14},{"nuance":"REC","nom":"ZEMMOUR","prenom":"Éric","voix":44,"elu":false,"pct":7.06},{"nuance":"VEC","nom":"JADOT","prenom":"Yannick","voix":21,"elu":false,"pct":3.37},{"nuance":"COM","nom":"ROUSSEL","prenom":"Fabien","voix":20,"elu":false,"pct":3.21},{"nuance":"DVD","nom":"DUPONT-AIGNAN","prenom":"Nicolas","voix":15,"elu":false,"pct":2.41},{"nuance":"LR","nom":"PÉCRESSE","prenom":"Valérie","voix":11,"elu":false,"pct":1.77},{"nuance":"DIV","nom":"LASSALLE","prenom":"Jean","voix":10,"elu":false,"pct":1.61},{"nuance":"SOC","nom":"HIDALGO","prenom":"Anne","voix":9,"elu":false,"pct":1.44},{"nuance":"EXG","nom":"ARTHAUD","prenom":"Nathalie","voix":8,"elu":false,"pct":1.28},{"nuance":"EXG","nom":"POUTOU","prenom":"Philippe","voix":3,"elu":false,"pct":0.48}],"participation":75.42,"libelle":"Complexe Sportif Et Culturel","adresse":"5 bis Rue Arago, 57255 Sainte Marie Aux Chenes","lat":49.190598,"lon":5.998183},{"bureau":"0004","inscrits":741,"votants":534,"abstentions":207,"exprimes":520,"blancs":9,"nuls":5,"results":[{"nuance":"RN","nom":"LE PEN","prenom":"Marine","voix":176,"elu":false,"pct":33.85},{"nuance":"ENS","nom":"MACRON","prenom":"Emmanuel","voix":142,"elu":false,"pct":27.31},{"nuance":"FI","nom":"MÉLENCHON","prenom":"Jean-Luc","voix":96,"elu":false,"pct":18.46},{"nuance":"REC","nom":"ZEMMOUR","prenom":"Éric","voix":36,"elu":false,"pct":6.92},{"nuance":"VEC","nom":"JADOT","prenom":"Yannick","voix":15,"elu":false,"pct":2.88},{"nuance":"COM","nom":"ROUSSEL","prenom":"Fabien","voix":13,"elu":false,"pct":2.5},{"nuance":"DIV","nom":"LASSALLE","prenom":"Jean","voix":12,"elu":false,"pct":2.31},{"nuance":"SOC","nom":"HIDALGO","prenom":"Anne","voix":8,"elu":false,"pct":1.54},{"nuance":"DVD","nom":"DUPONT-AIGNAN","prenom":"Nicolas","voix":7,"elu":false,"pct":1.35},{"nuance":"LR","nom":"PÉCRESSE","prenom":"Valérie","voix":6,"elu":false,"pct":1.15},{"nuance":"EXG","nom":"POUTOU","prenom":"Philippe","voix":6,"elu":false,"pct":1.15},{"nuance":"EXG","nom":"ARTHAUD","prenom":"Nathalie","voix":3,"elu":false,"pct":0.58}],"participation":72.06,"libelle":"Complexe Sportif Et Culturel","adresse":"5 BIS Rue Arago, 57255 Sainte Marie Aux Chenes","lat":49.190598,"lon":5.998183}],"tour2":[{"bureau":"0001","inscrits":752,"votants":549,"abstentions":203,"exprimes":506,"blancs":36,"nuls":7,"results":[{"nuance":"RN","nom":"LE PEN","prenom":"Marine","voix":279,"elu":false,"pct":55.14},{"nuance":"ENS","nom":"MACRON","prenom":"Emmanuel","voix":227,"elu":true,"pct":44.86}],"participation":73.01,"libelle":"Complexe Sportif Et Culturel","adresse":"5 bis Rue Arago, 57255 Sainte Marie Aux Chenes","lat":49.190598,"lon":5.998183},{"bureau":"0002","inscrits":766,"votants":587,"abstentions":179,"exprimes":549,"blancs":28,"nuls":10,"results":[{"nuance":"RN","nom":"LE PEN","prenom":"Marine","voix":345,"elu":false,"pct":62.84},{"nuance":"ENS","nom":"MACRON","prenom":"Emmanuel","voix":204,"elu":true,"pct":37.16}],"participation":76.63,"libelle":"Complexe Sportif Et Culturel","adresse":"5 bis Rue Arago, 57255 Sainte Marie Aux Chenes","lat":49.190598,"lon":5.998183},{"bureau":"0003","inscrits":843,"votants":629,"abstentions":214,"exprimes":573,"blancs":38,"nuls":18,"results":[{"nuance":"RN","nom":"LE PEN","prenom":"Marine","voix":295,"elu":false,"pct":51.48},{"nuance":"ENS","nom":"MACRON","prenom":"Emmanuel","voix":278,"elu":true,"pct":48.52}],"participation":74.61,"libelle":"Complexe Sportif Et Culturel","adresse":"5 bis Rue Arago, 57255 Sainte Marie Aux Chenes","lat":49.190598,"lon":5.998183},{"bureau":"0004","inscrits":743,"votants":539,"abstentions":204,"exprimes":507,"blancs":19,"nuls":13,"results":[{"nuance":"RN","nom":"LE PEN","prenom":"Marine","voix":275,"elu":false,"pct":54.24},{"nuance":"ENS","nom":"MACRON","prenom":"Emmanuel","voix":232,"elu":true,"pct":45.76}],"participation":72.54,"libelle":"Complexe Sportif Et Culturel","adresse":"5 BIS Rue Arago, 57255 Sainte Marie Aux Chenes","lat":49.190598,"lon":5.998183}]}}