{"code":"58099","nom":"Dommartin","legislatives":{"tour1":[{"bureau":"0001","inscrits":121,"votants":86,"abstentions":35,"exprimes":82,"blancs":2,"nuls":2,"results":[{"nuance":"RN","nom":"GUIBERT","prenom":"Julien","voix":42,"elu":false,"pct":51.22},{"nuance":"UG","nom":"PAUL","prenom":"Christian","voix":31,"elu":false,"pct":37.8},{"nuance":"ENS","nom":"GERMAIN","prenom":"Sandra","voix":7,"elu":false,"pct":8.54},{"nuance":"LR","nom":"VINCENT","prenom":"Marc Alexandre","voix":1,"elu":false,"pct":1.22},{"nuance":"DSV","nom":"MUNOZ","prenom":"Aurore","voix":1,"elu":false,"pct":1.22},{"nuance":"DVG","nom":"GUYOT","prenom":"Justine","voix":0,"elu":false,"pct":0},{"nuance":"EXG","nom":"DUPUIS","prenom":"Dominique","voix":0,"elu":false,"pct":0}],"participation":71.07,"libelle":"Mairie","adresse":"58120 Dommartin, 58120 Dommartin","lat":47.06947,"lon":3.840184}],"tour2":[{"bureau":"0001","inscrits":121,"votants":90,"abstentions":31,"exprimes":90,"blancs":0,"nuls":0,"results":[{"nuance":"RN","nom":"GUIBERT","prenom":"Julien","voix":49,"elu":true,"pct":54.44},{"nuance":"UG","nom":"PAUL","prenom":"Christian","voix":41,"elu":false,"pct":45.56}],"participation":74.38,"libelle":"Mairie","adresse":"58120 Dommartin, 58120 Dommartin","lat":47.06947,"lon":3.840184}]},"presidentielle":{"tour1":[{"bureau":"0001","inscrits":125,"votants":99,"abstentions":26,"exprimes":94,"blancs":4,"nuls":1,"results":[{"nuance":"RN","nom":"LE PEN","prenom":"Marine","voix":28,"elu":false,"pct":29.79},{"nuance":"ENS","nom":"MACRON","prenom":"Emmanuel","voix":22,"elu":false,"pct":23.4},{"nuance":"FI","nom":"MÉLENCHON","prenom":"Jean-Luc","voix":11,"elu":false,"pct":11.7},{"nuance":"DIV","nom":"LASSALLE","prenom":"Jean","voix":8,"elu":false,"pct":8.51},{"nuance":"REC","nom":"ZEMMOUR","prenom":"Éric","voix":8,"elu":false,"pct":8.51},{"nuance":"LR","nom":"PÉCRESSE","prenom":"Valérie","voix":5,"elu":false,"pct":5.32},{"nuance":"DVD","nom":"DUPONT-AIGNAN","prenom":"Nicolas","voix":4,"elu":false,"pct":4.26},{"nuance":"SOC","nom":"HIDALGO","prenom":"Anne","voix":3,"elu":false,"pct":3.19},{"nuance":"COM","nom":"ROUSSEL","prenom":"Fabien","voix":2,"elu":false,"pct":2.13},{"nuance":"EXG","nom":"POUTOU","prenom":"Philippe","voix":2,"elu":false,"pct":2.13},{"nuance":"VEC","nom":"JADOT","prenom":"Yannick","voix":1,"elu":false,"pct":1.06},{"nuance":"EXG","nom":"ARTHAUD","prenom":"Nathalie","voix":0,"elu":false,"pct":0}],"participation":79.2,"libelle":"Mairie","adresse":"58120 Dommartin, 58120 Dommartin","lat":47.06947,"lon":3.840184}],"tour2":[{"bureau":"0001","inscrits":123,"votants":100,"abstentions":23,"exprimes":89,"blancs":7,"nuls":4,"results":[{"nuance":"RN","nom":"LE PEN","prenom":"Marine","voix":55,"elu":false,"pct":61.8},{"nuance":"ENS","nom":"MACRON","prenom":"Emmanuel","voix":34,"elu":true,"pct":38.2}],"participation":81.3,"libelle":"Mairie","adresse":"58120 Dommartin, 58120 Dommartin","lat":47.06947,"lon":3.840184}]}}