{"code":"61240","nom":"Macé","legislatives":{"tour1":[{"bureau":"0001","inscrits":350,"votants":226,"abstentions":124,"exprimes":221,"blancs":4,"nuls":1,"results":[{"nuance":"RN","nom":"BELZIDSKY","prenom":"Nadine","voix":107,"elu":false,"pct":48.42},{"nuance":"UG","nom":"JOURDAN","prenom":"Chantal","voix":45,"elu":false,"pct":20.36},{"nuance":"ENS","nom":"CHAPELOTTE","prenom":"Patricia","voix":44,"elu":false,"pct":19.91},{"nuance":"DVC","nom":"CHEVALIER","prenom":"Manuela","voix":17,"elu":false,"pct":7.69},{"nuance":"EXG","nom":"PERCHET","prenom":"Camille","voix":3,"elu":false,"pct":1.36},{"nuance":"REC","nom":"LECOMTE","prenom":"Daniel","voix":3,"elu":false,"pct":1.36},{"nuance":"DSV","nom":"GÉNITEAU","prenom":"David","voix":1,"elu":false,"pct":0.45},{"nuance":"DVD","nom":"DURANDY","prenom":"Didier","voix":1,"elu":false,"pct":0.45}],"participation":64.57,"libelle":"Mairie","adresse":"61500 Mace","lat":48.641798,"lon":0.131201}],"tour2":[{"bureau":"0001","inscrits":350,"votants":224,"abstentions":126,"exprimes":208,"blancs":14,"nuls":2,"results":[{"nuance":"RN","nom":"BELZIDSKY","prenom":"Nadine","voix":118,"elu":false,"pct":56.73},{"nuance":"UG","nom":"JOURDAN","prenom":"Chantal","voix":90,"elu":true,"pct":43.27}],"participation":64,"libelle":"Mairie","adresse":"61500 Mace","lat":48.641798,"lon":0.131201}]},"presidentielle":{"tour1":[{"bureau":"0001","inscrits":355,"votants":240,"abstentions":115,"exprimes":233,"blancs":6,"nuls":1,"results":[{"nuance":"RN","nom":"LE PEN","prenom":"Marine","voix":73,"elu":false,"pct":31.33},{"nuance":"ENS","nom":"MACRON","prenom":"Emmanuel","voix":70,"elu":false,"pct":30.04},{"nuance":"FI","nom":"MÉLENCHON","prenom":"Jean-Luc","voix":25,"elu":false,"pct":10.73},{"nuance":"REC","nom":"ZEMMOUR","prenom":"Éric","voix":15,"elu":false,"pct":6.44},{"nuance":"VEC","nom":"JADOT","prenom":"Yannick","voix":11,"elu":false,"pct":4.72},{"nuance":"COM","nom":"ROUSSEL","prenom":"Fabien","voix":10,"elu":false,"pct":4.29},{"nuance":"LR","nom":"PÉCRESSE","prenom":"Valérie","voix":9,"elu":false,"pct":3.86},{"nuance":"DIV","nom":"LASSALLE","prenom":"Jean","voix":7,"elu":false,"pct":3},{"nuance":"DVD","nom":"DUPONT-AIGNAN","prenom":"Nicolas","voix":7,"elu":false,"pct":3},{"nuance":"EXG","nom":"ARTHAUD","prenom":"Nathalie","voix":2,"elu":false,"pct":0.86},{"nuance":"SOC","nom":"HIDALGO","prenom":"Anne","voix":2,"elu":false,"pct":0.86},{"nuance":"EXG","nom":"POUTOU","prenom":"Philippe","voix":2,"elu":false,"pct":0.86}],"participation":67.61,"libelle":"Mairie","adresse":"61500 Mace","lat":48.641798,"lon":0.131201}],"tour2":[{"bureau":"0001","inscrits":355,"votants":263,"abstentions":92,"exprimes":239,"blancs":19,"nuls":5,"results":[{"nuance":"RN","nom":"LE PEN","prenom":"Marine","voix":120,"elu":false,"pct":50.21},{"nuance":"ENS","nom":"MACRON","prenom":"Emmanuel","voix":119,"elu":true,"pct":49.79}],"participation":74.08,"libelle":"Mairie","adresse":"61500 Mace","lat":48.641798,"lon":0.131201}]}}