{"code":"64058","nom":"Arthez-d'Asson","legislatives":{"tour1":[{"bureau":"0001","inscrits":420,"votants":297,"abstentions":123,"exprimes":283,"blancs":10,"nuls":4,"results":[{"nuance":"RN","nom":"BECKER","prenom":"Monique","voix":111,"elu":false,"pct":39.22},{"nuance":"UG","nom":"BRUNEL","prenom":"Julien","voix":69,"elu":false,"pct":24.38},{"nuance":"ENS","nom":"MATTEÏ","prenom":"Jean-Paul","voix":54,"elu":false,"pct":19.08},{"nuance":"LR","nom":"LABAT","prenom":"Marc","voix":27,"elu":false,"pct":9.54},{"nuance":"REG","nom":"CESCAU","prenom":"Patrici","voix":16,"elu":false,"pct":5.65},{"nuance":"ECO","nom":"MAUHOURAT","prenom":"Jacques","voix":4,"elu":false,"pct":1.41},{"nuance":"EXG","nom":"MARCONI","prenom":"Cyrille","voix":2,"elu":false,"pct":0.71}],"participation":70.71,"libelle":"Bureau Unique","adresse":"Arthez-d'Asson","lat":null,"lon":null}],"tour2":[{"bureau":"0001","inscrits":420,"votants":308,"abstentions":112,"exprimes":276,"blancs":22,"nuls":10,"results":[{"nuance":"ENS","nom":"MATTEÏ","prenom":"Jean-Paul","voix":144,"elu":true,"pct":52.17},{"nuance":"RN","nom":"BECKER","prenom":"Monique","voix":132,"elu":false,"pct":47.83}],"participation":73.33,"libelle":"Bureau Unique","adresse":"Arthez-d'Asson","lat":null,"lon":null}]},"presidentielle":{"tour1":[{"bureau":"0001","inscrits":422,"votants":334,"abstentions":88,"exprimes":328,"blancs":5,"nuls":1,"results":[{"nuance":"RN","nom":"LE PEN","prenom":"Marine","voix":75,"elu":false,"pct":22.87},{"nuance":"ENS","nom":"MACRON","prenom":"Emmanuel","voix":57,"elu":false,"pct":17.38},{"nuance":"FI","nom":"MÉLENCHON","prenom":"Jean-Luc","voix":53,"elu":false,"pct":16.16},{"nuance":"DIV","nom":"LASSALLE","prenom":"Jean","voix":48,"elu":false,"pct":14.63},{"nuance":"REC","nom":"ZEMMOUR","prenom":"Éric","voix":45,"elu":false,"pct":13.72},{"nuance":"COM","nom":"ROUSSEL","prenom":"Fabien","voix":16,"elu":false,"pct":4.88},{"nuance":"DVD","nom":"DUPONT-AIGNAN","prenom":"Nicolas","voix":10,"elu":false,"pct":3.05},{"nuance":"VEC","nom":"JADOT","prenom":"Yannick","voix":7,"elu":false,"pct":2.13},{"nuance":"LR","nom":"PÉCRESSE","prenom":"Valérie","voix":7,"elu":false,"pct":2.13},{"nuance":"SOC","nom":"HIDALGO","prenom":"Anne","voix":5,"elu":false,"pct":1.52},{"nuance":"EXG","nom":"ARTHAUD","prenom":"Nathalie","voix":4,"elu":false,"pct":1.22},{"nuance":"EXG","nom":"POUTOU","prenom":"Philippe","voix":1,"elu":false,"pct":0.3}],"participation":79.15,"libelle":"Bureau Unique","adresse":"Arthez-d'Asson","lat":null,"lon":null}],"tour2":[{"bureau":"0001","inscrits":422,"votants":307,"abstentions":115,"exprimes":272,"blancs":24,"nuls":11,"results":[{"nuance":"RN","nom":"LE PEN","prenom":"Marine","voix":138,"elu":false,"pct":50.74},{"nuance":"ENS","nom":"MACRON","prenom":"Emmanuel","voix":134,"elu":true,"pct":49.26}],"participation":72.75,"libelle":"Bureau Unique","adresse":"Arthez-d'Asson","lat":null,"lon":null}]}}