{"code":"64339","nom":"Lestelle-Bétharram","tour1":[{"bureau":"0001","inscrits":607,"votants":460,"abstentions":147,"exprimes":449,"blancs":10,"nuls":1,"results":[{"nuance":"RN","nom":"BECKER","prenom":"Monique","voix":167,"elu":false,"pct":37.19},{"nuance":"UG","nom":"BRUNEL","prenom":"Julien","voix":113,"elu":false,"pct":25.17},{"nuance":"ENS","nom":"MATTEÏ","prenom":"Jean-Paul","voix":89,"elu":false,"pct":19.82},{"nuance":"LR","nom":"LABAT","prenom":"Marc","voix":56,"elu":false,"pct":12.47},{"nuance":"ECO","nom":"MAUHOURAT","prenom":"Jacques","voix":11,"elu":false,"pct":2.45},{"nuance":"REG","nom":"CESCAU","prenom":"Patrici","voix":7,"elu":false,"pct":1.56},{"nuance":"EXG","nom":"MARCONI","prenom":"Cyrille","voix":6,"elu":false,"pct":1.34}],"participation":75.78,"libelle":"Salle De L Isarce","adresse":"Rue Du Parc Des Sports, 64800 Lestelle Betharram","lat":43.129676,"lon":-0.208339}],"tour2":[{"bureau":"0001","inscrits":607,"votants":452,"abstentions":155,"exprimes":412,"blancs":24,"nuls":16,"results":[{"nuance":"ENS","nom":"MATTEÏ","prenom":"Jean-Paul","voix":224,"elu":true,"pct":54.37},{"nuance":"RN","nom":"BECKER","prenom":"Monique","voix":188,"elu":false,"pct":45.63}],"participation":74.46,"libelle":"Salle De L Isarce","adresse":"Rue Du Parc Des Sports, 64800 Lestelle Betharram","lat":43.129676,"lon":-0.208339}]}