{"code":"70195","nom":"Dambenoît-lès-Colombe","tour1":[{"bureau":"1","inscrits":238,"votants":174,"abstentions":64,"exprimes":167,"blancs":3,"nuls":4,"results":[{"nuance":"RN","nom":"SALMON","prenom":"Emeric","voix":76,"elu":true,"pct":45.51},{"nuance":"UG","nom":"HOULLEY","prenom":"Eric","voix":51,"elu":false,"pct":30.54},{"nuance":"LR","nom":"LABORIE","prenom":"Loic","voix":18,"elu":false,"pct":10.78},{"nuance":"ENS","nom":"BARASSI-ZAMOCHNIKOFF","prenom":"Fabrice","voix":12,"elu":false,"pct":7.19},{"nuance":"EXG","nom":"APRO","prenom":"Isabelle","voix":7,"elu":false,"pct":4.19},{"nuance":"REC","nom":"DEVILLERS","prenom":"Christophe","voix":3,"elu":false,"pct":1.8}],"participation":73.11,"libelle":null,"adresse":null,"lat":null,"lon":null}],"tour2":null}