{"code":"72118","nom":"Dollon","legislatives":{"tour1":[{"bureau":"0001","inscrits":1128,"votants":756,"abstentions":372,"exprimes":731,"blancs":12,"nuls":13,"results":[{"nuance":"RN","nom":"VAUGARNY","prenom":"Pierre","voix":403,"elu":false,"pct":55.13},{"nuance":"ENS","nom":"GRELIER","prenom":"Jean-Carles","voix":192,"elu":false,"pct":26.27},{"nuance":"UG","nom":"ROUILLON","prenom":"Christophe","voix":116,"elu":false,"pct":15.87},{"nuance":"EXG","nom":"FOUQUET","prenom":"Karine","voix":11,"elu":false,"pct":1.5},{"nuance":"DSV","nom":"BAYLE DE JESSÉ","prenom":"Cécile","voix":9,"elu":false,"pct":1.23}],"participation":67.02,"libelle":"Salle Polyvalente","adresse":"Rue De La Piscine, 72390 Dollon","lat":48.039426,"lon":0.592733}],"tour2":[{"bureau":"0001","inscrits":1127,"votants":769,"abstentions":358,"exprimes":733,"blancs":23,"nuls":13,"results":[{"nuance":"RN","nom":"VAUGARNY","prenom":"Pierre","voix":440,"elu":false,"pct":60.03},{"nuance":"ENS","nom":"GRELIER","prenom":"Jean-Carles","voix":293,"elu":true,"pct":39.97}],"participation":68.23,"libelle":"Salle Polyvalente","adresse":"Rue De La Piscine, 72390 Dollon","lat":48.039426,"lon":0.592733}]},"presidentielle":{"tour1":[{"bureau":"0001","inscrits":1160,"votants":853,"abstentions":307,"exprimes":831,"blancs":19,"nuls":3,"results":[{"nuance":"RN","nom":"LE PEN","prenom":"Marine","voix":328,"elu":false,"pct":39.47},{"nuance":"ENS","nom":"MACRON","prenom":"Emmanuel","voix":186,"elu":false,"pct":22.38},{"nuance":"FI","nom":"MÉLENCHON","prenom":"Jean-Luc","voix":129,"elu":false,"pct":15.52},{"nuance":"REC","nom":"ZEMMOUR","prenom":"Éric","voix":36,"elu":false,"pct":4.33},{"nuance":"LR","nom":"PÉCRESSE","prenom":"Valérie","voix":33,"elu":false,"pct":3.97},{"nuance":"DIV","nom":"LASSALLE","prenom":"Jean","voix":30,"elu":false,"pct":3.61},{"nuance":"VEC","nom":"JADOT","prenom":"Yannick","voix":28,"elu":false,"pct":3.37},{"nuance":"COM","nom":"ROUSSEL","prenom":"Fabien","voix":18,"elu":false,"pct":2.17},{"nuance":"DVD","nom":"DUPONT-AIGNAN","prenom":"Nicolas","voix":17,"elu":false,"pct":2.05},{"nuance":"EXG","nom":"ARTHAUD","prenom":"Nathalie","voix":11,"elu":false,"pct":1.32},{"nuance":"SOC","nom":"HIDALGO","prenom":"Anne","voix":8,"elu":false,"pct":0.96},{"nuance":"EXG","nom":"POUTOU","prenom":"Philippe","voix":7,"elu":false,"pct":0.84}],"participation":73.53,"libelle":"Salle Polyvalente","adresse":"Rue De La Piscine, 72390 Dollon","lat":48.039426,"lon":0.592733}],"tour2":[{"bureau":"0001","inscrits":1161,"votants":901,"abstentions":260,"exprimes":829,"blancs":45,"nuls":27,"results":[{"nuance":"RN","nom":"LE PEN","prenom":"Marine","voix":494,"elu":false,"pct":59.59},{"nuance":"ENS","nom":"MACRON","prenom":"Emmanuel","voix":335,"elu":true,"pct":40.41}],"participation":77.61,"libelle":"Salle Polyvalente","adresse":"Rue De La Piscine, 72390 Dollon","lat":48.039426,"lon":0.592733}]}}