{"code":"73033","nom":"La Bauche","tour1":[{"bureau":"1","inscrits":412,"votants":306,"abstentions":106,"exprimes":295,"blancs":2,"nuls":9,"results":[{"nuance":"UXD","nom":"DEGOIS","prenom":"Typhanie","voix":122,"elu":false,"pct":41.36},{"nuance":"UG","nom":"GRANATA","prenom":"Christel","voix":116,"elu":false,"pct":39.32},{"nuance":"ENS","nom":"FERRARI","prenom":"Marina","voix":45,"elu":false,"pct":15.25},{"nuance":"ECO","nom":"EXERTIER","prenom":"Frédéric","voix":10,"elu":false,"pct":3.39},{"nuance":"EXG","nom":"CASEJUANE","prenom":"Adrien","voix":2,"elu":false,"pct":0.68},{"nuance":"REC","nom":"PEYRARD","prenom":"Guy-Alain","voix":0,"elu":false,"pct":0},{"nuance":"DSV","nom":"CHAUVEAU","prenom":"Jean-Pierre","voix":0,"elu":false,"pct":0}],"participation":74.27,"libelle":null,"adresse":null,"lat":null,"lon":null}],"tour2":[{"bureau":"0001","inscrits":412,"votants":291,"abstentions":121,"exprimes":271,"blancs":15,"nuls":5,"results":[{"nuance":"UXD","nom":"DEGOIS","prenom":"Typhanie","voix":137,"elu":false,"pct":50.55},{"nuance":"ENS","nom":"FERRARI","prenom":"Marina","voix":134,"elu":true,"pct":49.45}],"participation":70.63,"libelle":"Bureau Unique","adresse":"2 Chemin Du Guillot, 73360 La Bauche","lat":45.482041,"lon":5.764966}]}