{"code":"78497","nom":"Poigny-la-Forêt","tour1":[{"bureau":"1","inscrits":734,"votants":615,"abstentions":119,"exprimes":606,"blancs":8,"nuls":1,"results":[{"nuance":"ENS","nom":"BERGÉ","prenom":"Aurore","voix":227,"elu":false,"pct":37.46},{"nuance":"RN","nom":"DU CHALARD","prenom":"Thomas","voix":206,"elu":false,"pct":33.99},{"nuance":"UG","nom":"BRIOLAIS","prenom":"Cédric","voix":72,"elu":false,"pct":11.88},{"nuance":"LR","nom":"BARBOTIN","prenom":"Gaël","voix":58,"elu":false,"pct":9.57},{"nuance":"ECO","nom":"FOURNIER-CAMPION","prenom":"Ethel","voix":15,"elu":false,"pct":2.48},{"nuance":"RDG","nom":"GAUTRELET","prenom":"Julien","voix":12,"elu":false,"pct":1.98},{"nuance":"REC","nom":"GOUSSEAU","prenom":"Olivier","voix":10,"elu":false,"pct":1.65},{"nuance":"EXG","nom":"JANISSET","prenom":"Hélène","voix":6,"elu":false,"pct":0.99}],"participation":83.79,"libelle":null,"adresse":null,"lat":null,"lon":null}],"tour2":[{"bureau":"0001","inscrits":734,"votants":606,"abstentions":128,"exprimes":590,"blancs":11,"nuls":5,"results":[{"nuance":"ENS","nom":"BERGÉ","prenom":"Aurore","voix":305,"elu":true,"pct":51.69},{"nuance":"RN","nom":"DU CHALARD","prenom":"Thomas","voix":235,"elu":false,"pct":39.83},{"nuance":"UG","nom":"BRIOLAIS","prenom":"Cédric","voix":50,"elu":false,"pct":8.47}],"participation":82.56,"libelle":"Bureau De Vote N 1","adresse":"11 Route De Rambouillet, 78125 Poigny La Foret","lat":48.677763,"lon":1.757479}]}