{"code":"85291","nom":"Thorigny","legislatives":{"tour1":[{"bureau":"0001","inscrits":921,"votants":641,"abstentions":280,"exprimes":612,"blancs":16,"nuls":13,"results":[{"nuance":"ENS","nom":"BELLAMY","prenom":"Béatrice","voix":230,"elu":false,"pct":37.58},{"nuance":"RN","nom":"EBRAN","prenom":"Marie-Christine","voix":218,"elu":false,"pct":35.62},{"nuance":"UG","nom":"HELARY","prenom":"Nicolas","voix":154,"elu":false,"pct":25.16},{"nuance":"EXG","nom":"BARILLOT","prenom":"Sophie","voix":10,"elu":false,"pct":1.63}],"participation":69.6,"libelle":"Mairie","adresse":"1 Place De L'Église, 85480 Thorigny","lat":46.61263,"lon":-1.241117}],"tour2":[{"bureau":"0001","inscrits":921,"votants":643,"abstentions":278,"exprimes":600,"blancs":30,"nuls":13,"results":[{"nuance":"ENS","nom":"BELLAMY","prenom":"Béatrice","voix":364,"elu":true,"pct":60.67},{"nuance":"RN","nom":"EBRAN","prenom":"Marie-Christine","voix":236,"elu":false,"pct":39.33}],"participation":69.82,"libelle":"Mairie","adresse":"1 Place De L'Église, 85480 Thorigny","lat":46.61263,"lon":-1.241117}]},"presidentielle":{"tour1":[{"bureau":"0001","inscrits":886,"votants":716,"abstentions":170,"exprimes":705,"blancs":8,"nuls":3,"results":[{"nuance":"ENS","nom":"MACRON","prenom":"Emmanuel","voix":215,"elu":false,"pct":30.5},{"nuance":"RN","nom":"LE PEN","prenom":"Marine","voix":175,"elu":false,"pct":24.82},{"nuance":"FI","nom":"MÉLENCHON","prenom":"Jean-Luc","voix":122,"elu":false,"pct":17.3},{"nuance":"VEC","nom":"JADOT","prenom":"Yannick","voix":42,"elu":false,"pct":5.96},{"nuance":"LR","nom":"PÉCRESSE","prenom":"Valérie","voix":40,"elu":false,"pct":5.67},{"nuance":"REC","nom":"ZEMMOUR","prenom":"Éric","voix":30,"elu":false,"pct":4.26},{"nuance":"DIV","nom":"LASSALLE","prenom":"Jean","voix":28,"elu":false,"pct":3.97},{"nuance":"DVD","nom":"DUPONT-AIGNAN","prenom":"Nicolas","voix":19,"elu":false,"pct":2.7},{"nuance":"SOC","nom":"HIDALGO","prenom":"Anne","voix":15,"elu":false,"pct":2.13},{"nuance":"COM","nom":"ROUSSEL","prenom":"Fabien","voix":14,"elu":false,"pct":1.99},{"nuance":"EXG","nom":"ARTHAUD","prenom":"Nathalie","voix":3,"elu":false,"pct":0.43},{"nuance":"EXG","nom":"POUTOU","prenom":"Philippe","voix":2,"elu":false,"pct":0.28}],"participation":80.81,"libelle":"Mairie","adresse":"1 Place De L'Église, 85480 Thorigny","lat":46.61263,"lon":-1.241117}],"tour2":[{"bureau":"0001","inscrits":887,"votants":718,"abstentions":169,"exprimes":653,"blancs":45,"nuls":20,"results":[{"nuance":"ENS","nom":"MACRON","prenom":"Emmanuel","voix":398,"elu":true,"pct":60.95},{"nuance":"RN","nom":"LE PEN","prenom":"Marine","voix":255,"elu":false,"pct":39.05}],"participation":80.95,"libelle":"Mairie","adresse":"1 Place De L'Église, 85480 Thorigny","lat":46.61263,"lon":-1.241117}]}}