{"code":"86116","nom":"Jazeneuil","tour1":[{"bureau":"0001","inscrits":617,"votants":449,"abstentions":168,"exprimes":421,"blancs":19,"nuls":9,"results":[{"nuance":"RN","nom":"SOULAT","prenom":"Eric","voix":148,"elu":false,"pct":35.15},{"nuance":"UG","nom":"JEAN","prenom":"Gisèle","voix":140,"elu":false,"pct":33.25},{"nuance":"ENS","nom":"LECAMP","prenom":"Pascal","voix":124,"elu":false,"pct":29.45},{"nuance":"EXG","nom":"JOUAN","prenom":"Soizic","voix":5,"elu":false,"pct":1.19},{"nuance":"ECO","nom":"GOUVERNEUR","prenom":"Tatiana","voix":4,"elu":false,"pct":0.95}],"participation":72.77,"libelle":"Salle Des Fetes","adresse":"Place De La Morinerie, 86600 Jazeneuil","lat":46.465883,"lon":0.068541}],"tour2":[{"bureau":"0001","inscrits":616,"votants":447,"abstentions":169,"exprimes":418,"blancs":21,"nuls":8,"results":[{"nuance":"ENS","nom":"LECAMP","prenom":"Pascal","voix":259,"elu":true,"pct":61.96},{"nuance":"RN","nom":"SOULAT","prenom":"Eric","voix":159,"elu":false,"pct":38.04}],"participation":72.56,"libelle":"Salle Des Fetes","adresse":"Place De La Morinerie, 86600 Jazeneuil","lat":46.465883,"lon":0.068541}]}