{"code":"88216","nom":"Grandvillers","tour1":[{"bureau":"0001","inscrits":515,"votants":371,"abstentions":144,"exprimes":357,"blancs":11,"nuls":3,"results":[{"nuance":"RN","nom":"DUSSAUSAYE","prenom":"Gaëtan","voix":191,"elu":false,"pct":53.5},{"nuance":"ENS","nom":"VALENCE","prenom":"David","voix":108,"elu":false,"pct":30.25},{"nuance":"UG","nom":"XICOLA","prenom":"Julie","voix":44,"elu":false,"pct":12.32},{"nuance":"DVC","nom":"THIEBAUT","prenom":"Emmanuel","voix":9,"elu":false,"pct":2.52},{"nuance":"EXG","nom":"LANGLADE","prenom":"Jeanne-Françoise","voix":3,"elu":false,"pct":0.84},{"nuance":"LR","nom":"GATEAU","prenom":"Emma","voix":2,"elu":false,"pct":0.56},{"nuance":"ECO","nom":"CHAMBROT","prenom":"Lionel","voix":0,"elu":false,"pct":0}],"participation":72.04,"libelle":"Mairie","adresse":"28 Rue De La Mairie, 88600 Grandvillers","lat":48.238959,"lon":6.667205}],"tour2":[{"bureau":"0001","inscrits":515,"votants":394,"abstentions":121,"exprimes":382,"blancs":10,"nuls":2,"results":[{"nuance":"RN","nom":"DUSSAUSAYE","prenom":"Gaëtan","voix":217,"elu":true,"pct":56.81},{"nuance":"ENS","nom":"VALENCE","prenom":"David","voix":165,"elu":false,"pct":43.19}],"participation":76.5,"libelle":"Mairie","adresse":"28 Rue De La Mairie, 88600 Grandvillers","lat":48.238959,"lon":6.667205}]}